quaero/__init__.py
quaero/consts.py
quaero/index.py
quaero/openai.py
quaero/utils.py
quaero-1.1.5.dist-info/METADATA
quaero-1.1.5.dist-info/WHEEL
quaero-1.1.5.dist-info/entry_points.txt
quaero-1.1.5.dist-info/top_level.txt
quaero-1.1.5.dist-info/RECORD
