Metadata-Version: 2.1
Name: quaero
Version: 1.1.5
Summary: Simple CLI tool for asking ChatGPT questions in the CLI
Home-page: https://github.com/yeo-yeo/chatgpt-cli-python
Author: Gillian Yeomans
Author-email: hello@gillian.codes
Requires-Dist: aiohttp
Requires-Dist: colorama
Requires-Dist: python-dotenv
